github_clones_badge/__init__.py
github_clones_badge/get_github_clones.py
github_clones_badge/badges/README.md
github_clones_badge/data/README.md
github_clones_badge-0.1.3.data/data/badges/README.md
github_clones_badge-0.1.3.data/data/data/README.md
github_clones_badge-0.1.3.dist-info/DESCRIPTION.rst
github_clones_badge-0.1.3.dist-info/METADATA
github_clones_badge-0.1.3.dist-info/RECORD
github_clones_badge-0.1.3.dist-info/WHEEL
github_clones_badge-0.1.3.dist-info/metadata.json
github_clones_badge-0.1.3.dist-info/top_level.txt
