Metadata-Version: 2.0
Name: github-clones-badge
Version: 0.1.3
Summary: A small package to create badges that count github clones
Home-page: https://github.com/apmechev/github_clones_badge
Author: Alexandar Mechev
Author-email: apmechev@gmail.com
License: UNKNOWN
Download-URL: https://github.com/apmechev/github_clones_badge/archive/v0.1.0.tar.gz
Keywords: github,github_badges,developer_tools
Platform: UNKNOWN
Classifier: Development Status :: 3 - Alpha
Classifier: Intended Audience :: Developers
Classifier: License :: OSI Approved :: GNU General Public License v3 (GPLv3)
Classifier: Natural Language :: English
Classifier: Topic :: Software Development :: Documentation
Classifier: Topic :: Software Development :: Widget Sets
Classifier: Topic :: Utilities
Classifier: Programming Language :: Python :: 2.6
Classifier: Programming Language :: Python :: 2.7
Classifier: Programming Language :: Python :: 3
Classifier: Programming Language :: Python :: 3.2
Classifier: Programming Language :: Python :: 3.3
Classifier: Programming Language :: Python :: 3.4
Requires-Dist: python-crontab
Requires-Dist: requests (==2.18.4)
